api_key_rotator/__init__.py
api_key_rotator/exceptions.py
api_key_rotator/handler.py
api_key_rotator/utils.py
amazon_cloudfront_api_key_rotator-0.1.0.dist-info/LICENSE
amazon_cloudfront_api_key_rotator-0.1.0.dist-info/METADATA
amazon_cloudfront_api_key_rotator-0.1.0.dist-info/WHEEL
amazon_cloudfront_api_key_rotator-0.1.0.dist-info/top_level.txt
amazon_cloudfront_api_key_rotator-0.1.0.dist-info/RECORD
